README.md
setup.cfg
setup.py
evolvcli/__init__.py
evolvcli/cli.py
evolvcli.egg-info/PKG-INFO
evolvcli.egg-info/SOURCES.txt
evolvcli.egg-info/dependency_links.txt
evolvcli.egg-info/entry_points.txt
evolvcli.egg-info/requires.txt
evolvcli.egg-info/top_level.txt
evolvcli/sdk/__init__.py
evolvcli/sdk/setup.py
evolvcli/sdk/evolvclient/__init__.py
evolvcli/sdk/evolvclient/client.py
evolvcli/sdk/evolvclient/collections.py
evolvcli/sdk/evolvclient/config.py
evolvcli/sdk/evolvclient/request.py
evolvcli/sdk/evolvclient/util.py
evolvcli/sdk/evolvclient/tests/__init__.py
evolvcli/sdk/evolvclient/tests/test_client.py
evolvcli/sdk/evolvclient/tests/test_config.py
evolvcli/sdk/evolvclient/tests/test_evolv_request.py
evolvcli/sdk/scratch/__init__.py
evolvcli/sdk/scratch/sdk.py