Metadata-Version: 2.1
Name: evolvcli
Version: 1.0.3
Summary: CLI user for creating and maintaining Evolv experiments.
Home-page: https://github.com/evolv-ai/experiment-management-cli
Author: Frazer Bayley
Author-email: frazer.bayley@evolv.ai
License: Apache License 2.0
Download-URL: https://github.com/evolv-ai/experiment-management-cli/archive/1.0.0.tar.gz
Keywords: cli,Evolv,experiments,optimization
Platform: UNKNOWN
Classifier: Development Status :: 5 - Production/Stable
Classifier: Intended Audience :: Developers
Classifier: Intended Audience :: System Administrators
Classifier: Natural Language :: English
Classifier: Topic :: Software Development :: Build Tools
Classifier: License :: OSI Approved :: Apache Software License
Classifier: Programming Language :: Python :: 3.7
